{
    "day18": [
        { "number": 1, "eng": "check in", "kor1": "체크인하다", "kor2": "무료의", "correctAnswer": "체크인하다" },
        { "number": 2, "eng": "compensate", "kor1": "보상하다", "kor2": "체크인하다", "correctAnswer": "보상하다" },
        { "number": 3, "eng": "complimentary", "kor1": "무료의", "kor2": "우아한", "correctAnswer": "무료의" },
        { "number": 4, "eng": "chef", "kor1": "주방장", "kor2": "용기", "correctAnswer": "주방장" },
        { "number": 5, "eng": "container", "kor1": "용기", "kor2": "맛", "correctAnswer": "용기" },
        { "number": 6, "eng": "elegant", "kor1": "우아한", "kor2": "다과", "correctAnswer": "우아한" },
        { "number": 7, "eng": "flavor", "kor1": "맛", "kor2": "숙박 수속", "correctAnswer": "맛" },
        { "number": 8, "eng": "accommodate", "kor1": "수용하다", "kor2": "확인하다", "correctAnswer": "수용하다" },
        { "number": 9, "eng": "available", "kor1": "이용 가능한", "kor2": "예약하다", "correctAnswer": "이용 가능한" },
        { "number": 10, "eng": "reception", "kor1": "환영회", "kor2": "편의 시설", "correctAnswer": "환영회" },
        { "number": 11, "eng": "in advance", "kor1": "미리", "kor2": "예약하다", "correctAnswer": "미리" },
        { "number": 12, "eng": "refreshments", "kor1": "다과", "kor2": "조식", "correctAnswer": "다과" },
        { "number": 13, "eng": "make", "kor1": "만들다", "kor2": "장식하다", "correctAnswer": "만들다" },
        { "number": 14, "eng": "cater", "kor1": "음식물을 공급하다", "kor2": "확인하다", "correctAnswer": "음식물을 공급하다" },
        { "number": 15, "eng": "reservation", "kor1": "예약", "kor2": "정보", "correctAnswer": "예약" },
        { "number": 16, "eng": "beverage", "kor1": "음료", "kor2": "소지품", "correctAnswer": "음료" },
        { "number": 17, "eng": "confirm", "kor1": "확인하다", "kor2": "취소하다", "correctAnswer": "확인하다" },
        { "number": 18, "eng": "cancel", "kor1": "취소하다", "kor2": "보상하다", "correctAnswer": "취소하다" },
        { "number": 19, "eng": "rate", "kor1": "요금", "kor2": "무료의", "correctAnswer": "요금" },
        { "number": 20, "eng": "conveniently", "kor1": "편리하게", "kor2": "광범위한", "correctAnswer": "편리하게" },
        { "number": 21, "eng": "decorate", "kor1": "장식하다", "kor2": "다과", "correctAnswer": "장식하다" },
        { "number": 22, "eng": "information", "kor1": "정보", "kor2": "조치", "correctAnswer": "정보" },
        { "number": 23, "eng": "retain", "kor1": "유지하다", "kor2": "변경하다", "correctAnswer": "유지하다" },
        { "number": 24, "eng": "atmosphere", "kor1": "분위기", "kor2": "주방장", "correctAnswer": "분위기" },
        { "number": 25, "eng": "cuisine", "kor1": "요리", "kor2": "체크인하다", "correctAnswer": "요리" },
        { "number": 26, "eng": "sequence", "kor1": "순서", "kor2": "시점", "correctAnswer": "순서" },
        { "number": 27, "eng": "extensive", "kor1": "광범위한", "kor2": "소지품", "correctAnswer": "광범위한" },
        { "number": 28, "eng": "prior", "kor1": "전의", "kor2": "수용하다", "correctAnswer": "전의" },
        { "number": 29, "eng": "book", "kor1": "예약하다", "kor2": "기타", "correctAnswer": "예약하다" },
        { "number": 30, "eng": "amenity", "kor1": "편의 시설", "kor2": "다과", "correctAnswer": "편의 시설" },
        { "number": 31, "eng": "belongings", "kor1": "소지품", "kor2": "편의", "correctAnswer": "소지품" },
        { "number": 32, "eng": "entirely", "kor1": "완전히", "kor2": "조식", "correctAnswer": "완전히" },
        { "number": 33, "eng": "ease", "kor1": "완화시키다", "kor2": "장식하다", "correctAnswer": "완화시키다" },
        { "number": 34, "eng": "ingredient", "kor1": "재료", "kor2": "공급하다", "correctAnswer": "재료" },
        { "number": 35, "eng": "sip", "kor1": "음미하며 마시다", "kor2": "스푼", "correctAnswer": "음미하며 마시다" },
        { "number": 36, "eng": "stir", "kor1": "휘젓다", "kor2": "체크인하다", "correctAnswer": "휘젓다" },
        { "number": 37, "eng": "choice", "kor1": "선택물", "kor2": "소지품", "correctAnswer": "선택물" },
        { "number": 38, "eng": "complication", "kor1": "복잡한 문제", "kor2": "복잡한 기계", "correctAnswer": "복잡한 문제" },
        { "number": 39, "eng": "freshness", "kor1": "신선함", "kor2": "광범위한", "correctAnswer": "신선함" },
        { "number": 40, "eng": "occupancy", "kor1": "이용률", "kor2": "소지품", "correctAnswer": "이용률" }
    ]
}
